scg/__init__.py
scg/cli.py
scg/encrypt.py
scg/logo.py
scg/main.py
scg/config/__init__.py
scg/content/__init__.py
scg/content/handler.py
scg/content/helper.py
scg/content/message.py
scg/content/social_media.py
scg/csvreader/CSVReader.py
scg/csvreader/__init__.py
scg/sender/__init__.py
scg/sender/send_mail.py
scg-0.0.4.dist-info/LICENSE
scg-0.0.4.dist-info/METADATA
scg-0.0.4.dist-info/WHEEL
scg-0.0.4.dist-info/entry_points.txt
scg-0.0.4.dist-info/top_level.txt
scg-0.0.4.dist-info/RECORD
