Metadata-Version: 2.1
Name: scg
Version: 0.0.4
Summary: Send custom Gmail with Python
Home-page: https://github.com/scgorg/scg
Author: JunWei Song
Author-email: sungboss2004@gmail.com
License: UNKNOWN
Platform: UNKNOWN
Classifier: Programming Language :: Python :: 3
Classifier: License :: OSI Approved :: GNU General Public License v3 (GPLv3)
Classifier: Operating System :: OS Independent
Requires-Python: >=3.8
License-File: LICENSE
Requires-Dist: click
Requires-Dist: pycryptodome
